flask_pymongo/__init__.py
flask_pymongo/helpers.py
flask_pymongo/py.typed
flask_pymongo/wrappers.py
flask_pymongo-3.0.0.dist-info/METADATA
flask_pymongo-3.0.0.dist-info/WHEEL
flask_pymongo-3.0.0.dist-info/licenses/LICENSE
flask_pymongo-3.0.0.dist-info/RECORD
