Metadata-Version: 2.4
Name: Flask-PyMongo
Version: 3.0.0
Summary: PyMongo support for Flask applications
Project-URL: Download, https://github.com/mongodb-labs/flask-pymongo/tags
Project-URL: Homepage, http://flask-pymongo.readthedocs.org/
Author-email: Dan Crosta <dcrosta@late.am>
License: Copyright (c) 2011-2017, Dan Crosta
License-File: LICENSE
Classifier: Environment :: Web Environment
Classifier: Framework :: Flask
Classifier: Intended Audience :: Developers
Classifier: License :: OSI Approved :: BSD License
Classifier: Operating System :: OS Independent
Classifier: Programming Language :: Python :: 3.9
Classifier: Programming Language :: Python :: 3.10
Classifier: Programming Language :: Python :: 3.11
Classifier: Programming Language :: Python :: 3.12
Classifier: Programming Language :: Python :: 3.13
Classifier: Programming Language :: Python :: Implementation :: CPython
Classifier: Programming Language :: Python :: Implementation :: PyPy
Classifier: Topic :: Internet :: WWW/HTTP :: Dynamic Content
Classifier: Topic :: Software Development :: Libraries :: Python Modules
Requires-Python: >=3.9
Requires-Dist: flask>=3.0
Requires-Dist: pymongo>=4.0
